pyrise/__init__.py
pyrise/__main__.py
pyrise/cli.py
pyrise/data.py
pyrise/downloads.py
pyrise/indexfiles.py
pyrise/labels.py
pyrise/products.py
hirise_tools-0.7.3.dist-info/AUTHORS.rst
hirise_tools-0.7.3.dist-info/LICENSE
hirise_tools-0.7.3.dist-info/METADATA
hirise_tools-0.7.3.dist-info/WHEEL
hirise_tools-0.7.3.dist-info/entry_points.txt
hirise_tools-0.7.3.dist-info/top_level.txt
hirise_tools-0.7.3.dist-info/RECORD
