Metadata-Version: 2.1
Name: hirise-tools
Version: 0.7.3
Summary: Tools to work with MRO's HiRISE camera data.
Home-page: https://github.com/michaelaye/pyrise
Author: K.-Michael Aye
Author-email: kmichael.aye@gmail.com
License: ISC license
Keywords: HiRISE,MRO,NASA,PDS
Platform: UNKNOWN
Classifier: Development Status :: 2 - Pre-Alpha
Classifier: Intended Audience :: Developers
Classifier: Intended Audience :: Science/Research
Classifier: License :: OSI Approved :: ISC License (ISCL)
Classifier: Operating System :: Unix
Classifier: Operating System :: POSIX
Classifier: Operating System :: Microsoft :: Windows
Classifier: Programming Language :: Python
Classifier: Programming Language :: Python :: 3.6
Classifier: Topic :: Utilities
Requires-Dist: Click (>=6.0)
